pydanclick/__init__.py
pydanclick/command.py
pydanclick/main.py
pydanclick/model/__init__.py
pydanclick/model/docstrings.py
pydanclick/model/field_collection.py
pydanclick/model/field_conversion.py
pydanclick/model/model_conversion.py
pydanclick/model/type_conversion.py
pydanclick/model/validation.py
pydanclick/py.typed
pydanclick/types.py
pydanclick/utils.py
pydanclick-0.5.1.dist-info/LICENSE
pydanclick-0.5.1.dist-info/METADATA
pydanclick-0.5.1.dist-info/WHEEL
pydanclick-0.5.1.dist-info/RECORD
