Metadata-Version: 2.3
Name: pydanclick
Version: 0.5.1
Summary: Use Pydantic models as Click options
Author: Félix Martel
Author-email: felix.martel@polytechnique.edu>
Requires-Python: >=3.9,<4.0
Classifier: Programming Language :: Python :: 3
Classifier: Programming Language :: Python :: 3.9
Classifier: Programming Language :: Python :: 3.10
Classifier: Programming Language :: Python :: 3.11
Classifier: Programming Language :: Python :: 3.12
Classifier: Programming Language :: Python :: 3.13
Provides-Extra: griffe
Requires-Dist: griffe ; extra == "griffe"
Project-URL: Documentation, https://felix-martel.github.io/pydanclick/
Project-URL: Issues, https://github.com/felix-martel/pydanclick/issues
Project-URL: Repository, https://github.com/felix-martel/pydanclick.git
